{
    "name": "Twenty Trials",
    "id": 98780627,
    "author": "morpe",
    "creators": [
        "morpe"
    ],
    "verifier": "dwunco",
    "verification": "https://youtu.be/kTnqexYZXkY",
    "percentToQualify": 100,
    "password": "Free Copy",
    "records": [],
    "tags": [],
    "history": [
        {
            "date": "2026-07-24",
            "type": "moved",
            "oldPlacement": 15,
            "placement": 16,
            "notes": "i wanna be tombstone was added above"
        },
        {
            "date": "2026-07-22",
            "type": "added",
            "placement": 15,
            "notes": "Twenty Trials added to the list"
        }
    ],
    "rank": "beginner"
}