{
    "id": 13519,
    "name": "The Nightmare",
    "author": "Jax",
    "creators": [
        "Jax"
    ],
    "verifier": "dwunco",
    "verification": "https://youtu.be/i0dlZgqA8ds",
    "percentToQualify": 100,
    "password": "7813",
    "records": [
        {
            "user": "IShowMonkeyGMD",
            "link": "https://youtu.be/null",
            "percent": 100,
            "hz": 60,
            "mobile": true
        },
        {
            "user": "PixelPro11",
            "link": "https://youtu.be/null",
            "percent": 100,
            "hz": 60,
            "mobile": true
        },
        {
            "user": "aCUB3R",
            "link": "https://youtu.be/null",
            "percent": 100,
            "hz": 60
        },
        {
            "user": "hd123401",
            "link": "https://youtu.be/null",
            "percent": 100,
            "hz": 60
        },
        {
            "user": "WawLzerz",
            "link": "https://youtu.be/null",
            "percent": 100,
            "hz": 60
        },
        {
            "user": "cookiedarookie",
            "link": "https://youtu.be/null",
            "percent": 100,
            "hz": 144
        },
        {
            "user": "Fragment1345",
            "link": "https://youtu.be/null",
            "percent": 100,
            "hz": 60
        },
        {
            "user": "aThingToEx",
            "link": "https://youtu.be/null",
            "percent": 100,
            "hz": 60
        },
        {
            "user": "hxavenlydxvil",
            "link": "https://youtu.be/null",
            "percent": 100,
            "hz": 60
        },
        {
            "user": "nav.md",
            "link": "https://youtu.be/null",
            "percent": 100,
            "hz": 60
        }
    ],
    "history": [
        {
            "date": "2026-06-12",
            "type": "moved",
            "oldPlacement": 177,
            "placement": 178,
            "notes": "Azurite was added above"
        },
        {
            "date": "2026-06-11",
            "type": "moved",
            "oldPlacement": 176,
            "placement": 177,
            "notes": "Water Temple was added above"
        },
        {
            "date": "2026-06-07",
            "type": "moved",
            "oldPlacement": 175,
            "placement": 176,
            "notes": "Fire Temple was added above"
        },
        {
            "date": "2026-06-06",
            "type": "moved",
            "oldPlacement": 174,
            "placement": 175,
            "notes": "DNIDs Fantastic Ride was added above"
        },
        {
            "date": "2026-06-05",
            "type": "moved",
            "oldPlacement": 173,
            "placement": 174,
            "notes": "IDEOLOOCHY was added above"
        },
        {
            "date": "2026-06-05",
            "type": "moved",
            "oldPlacement": 172,
            "placement": 173,
            "notes": "Ladaschi was added above"
        },
        {
            "date": "2026-06-05",
            "type": "moved",
            "oldPlacement": 171,
            "placement": 172,
            "notes": "Blend Travel was added above"
        },
        {
            "date": "2026-06-05",
            "type": "moved",
            "oldPlacement": 170,
            "placement": 171,
            "notes": "BLOCKVEMBER was added above"
        },
        {
            "date": "2026-06-05",
            "type": "moved",
            "oldPlacement": 169,
            "placement": 170,
            "notes": "frequent visitor was added above"
        },
        {
            "date": "2026-06-05",
            "type": "moved",
            "oldPlacement": 168,
            "placement": 169,
            "notes": "Aurora Veil was added above"
        },
        {
            "date": "2026-06-05",
            "type": "moved",
            "oldPlacement": 167,
            "placement": 168,
            "notes": "StyX was added above"
        },
        {
            "date": "2026-06-05",
            "type": "moved",
            "oldPlacement": 166,
            "placement": 167,
            "notes": "weird was added above"
        },
        {
            "date": "2026-06-04",
            "type": "moved",
            "oldPlacement": 165,
            "placement": 166,
            "notes": "NothinG was added above"
        },
        {
            "date": "2026-06-04",
            "type": "moved",
            "oldPlacement": 164,
            "placement": 165,
            "notes": "Tabby was added above"
        },
        {
            "date": "2026-06-04",
            "type": "moved",
            "oldPlacement": 163,
            "placement": 164,
            "notes": "Nether step was added above"
        },
        {
            "date": "2026-06-04",
            "type": "moved",
            "oldPlacement": 162,
            "placement": 163,
            "notes": "Dystopia was added above"
        },
        {
            "date": "2026-06-04",
            "type": "moved",
            "oldPlacement": 161,
            "placement": 162,
            "notes": "Skyline Pt II was added above"
        },
        {
            "date": "2026-06-03",
            "type": "moved",
            "oldPlacement": 160,
            "placement": 161,
            "notes": "HelioPOSSIBLE was added above"
        },
        {
            "date": "2026-06-02",
            "type": "moved",
            "oldPlacement": 159,
            "placement": 160,
            "notes": "Sweater Weather was added above"
        },
        {
            "date": "2026-06-01",
            "type": "moved",
            "oldPlacement": 158,
            "placement": 159,
            "notes": "Nilscapes was added above"
        },
        {
            "date": "2026-06-01",
            "type": "moved",
            "oldPlacement": 157,
            "placement": 158,
            "notes": "Robi was added above"
        }
    ]
}