{
    "id": 83444471,
    "name": "WELL RESTED",
    "author": "100foxes",
    "creators": [
        "100foxes"
    ],
    "verifier": "cookiedarookie",
    "verification": "https://youtu.be/bM6V_JeSmeg",
    "percentToQualify": 100,
    "password": "NA",
    "records": [],
    "history": [
        {
            "date": "2026-06-11",
            "type": "moved",
            "oldPlacement": 70,
            "placement": 71,
            "notes": "Water Temple was added above"
        },
        {
            "date": "2026-06-07",
            "type": "moved",
            "oldPlacement": 69,
            "placement": 70,
            "notes": "Fire Temple was added above"
        },
        {
            "date": "2026-06-03",
            "type": "moved",
            "oldPlacement": 68,
            "placement": 69,
            "notes": "HelioPOSSIBLE was added above"
        },
        {
            "date": "2026-06-02",
            "type": "moved",
            "oldPlacement": 67,
            "placement": 68,
            "notes": "Sweater Weather was added above"
        },
        {
            "date": "2026-06-01",
            "type": "moved",
            "oldPlacement": 66,
            "placement": 67,
            "notes": "Nilscapes was added above"
        },
        {
            "date": "2026-06-01",
            "type": "moved",
            "oldPlacement": 65,
            "placement": 66,
            "notes": "Robi was added above"
        }
    ]
}